Workbook

Sheet README
A1: Tenaball: collected EPL data
A2: Collected 1 Oct 2026 for Tenaball. This is research data, not finished questions.
A4: Instructions for Claude Code (TENEBALL chat)
A5: This is collected data from Craig. Analyse it and incorporate it into new Tenaball questions however you see fit.
A6: Follow the existing Tenaball rules: every question states its period as a line under the question; no answer in 4 or more slots; PL player/goal data counts from 1992/93.
A7: Where several entries tie at the bottom of a list, every tied entry is included so any of them can count as a valid answer. Tied entries at the cut-off are highlighted yellow.
A8: Rows marked 'Next' or 'Just outside' are reserves and are NOT valid answers to a top-10 question.
A10: Data currency
A11: 2025/26 is the last complete season. 2026/27 is five matchweeks in; the next round is 10 to 12 Oct 2026.
A12: Live lists that can change: manager wins, points and win % (Moyes, Arteta, Maresca active), hat-tricks, Welbeck's seasons count.
A13: Guardiola left Man City in May 2026 (Maresca replaced him); Slot left Liverpool (Iraola); Milner retired June 2026. Their figures are final.
A15: Fee basis for transfer tabs
... A39: Sources: Main sources

Sheet Mgr Wins
A1: Most Premier League games won as manager
A2: Premier League only, 1992/93 to present (as at 1 Oct 2026; 2026/27 to matchweek 5)
A4: Rank | B4: Manager | C4: Wins | D4: Games | E4: Clubs / period
A5: 1 | B5: Alex Ferguson | C5: 528 | D5: 810 | E5: Man Utd 1992-2013
A6: 2 | B6: Arsène Wenger | C6: 476 | D6: 828 | E6: Arsenal 1996-2018
A7: 3 | B7: David Moyes (active) | C7: 292 | D7: 759 | E7: Everton, Man Utd, Sunderland, West Ham, Everton
A8: 4 | B8: Pep Guardiola | C8: 269 | D8: 380 | E8: Man City 2016-2026
A9: 5 | B9: Harry Redknapp | C9: 236 | D9: 641 | E9: West Ham, Portsmouth, Southampton, Spurs, QPR
A10: 6 | B10: José Mourinho | C10: 217 | D10: 363 | E10: Chelsea, Man Utd, Spurs
A11: 7 | B11: Jürgen Klopp | C11: 209 | D11: 334 | E11: Liverpool 2015-2024
A12: 8 | B12: Sam Allardyce | C12: 178 | D12: 541 | E12: 9 clubs, 2001-2023
A13: 9 | B13: Rafael Benítez | C13: 173 | D13: 359 | E13: Liverpool, Chelsea, Newcastle, Everton
A14: 10 | B14: Mark Hughes | C14: 158 | D14: 466 | E14: 6 clubs, 2004-2018
A15: Next | B15: Mikel Arteta (active) | C15: 153 | D15: 253 | E15: Arsenal; 5 wins short of Hughes, could enter this season
A16: Next | B16: Mauricio Pochettino | C16: 150 | D16: 294
A17: Next | B17: Eddie Howe | C17: 140 | D17: 369
A19: Notes
A20: No tie at 10th.
A21: Source gaps: StatMuse shows 1 fewer win for Moyes, Guardiola and Hughes; official/club figures used here.

Sheet Mgr Points
A1: Most Premier League points as manager
A2: Premier League only, 1992/93 to present (as at 1 Oct 2026; 2026/27 to matchweek 5)
A4: Rank | B4: Manager | C4: Points | D4: W-D-L | E4: Notes
A5: 1 | B5: Alex Ferguson | C5: 1752 | D5: 528-168-114
A6: 2 | B6: Arsène Wenger | C6: 1627 | D6: 476-199-153
A7: 3 | B7: David Moyes (active) | C7: 1078 | D7: 292-202-265
A8: 4 | B8: Harry Redknapp | C8: 876 | D8: 236-168-239 | E8: May be +/-2
A9: 5 | B9: Pep Guardiola | C9: 865 | D9: 269-58-53 | E9: Final
A10: 6 | B10: José Mourinho | C10: 735 | D10: 217-84-62
A11: 7 | B11: Jürgen Klopp | C11: 705 | D11: 209-78-47
A12: 8 | B12: Sam Allardyce | C12: 680 | D12: 178-146-218 | E12: May be +/-1
A13: 9 | B13: Rafael Benítez | C13: 605 | D13: 173-86-100
A14: 10 | B14: Mark Hughes | C14: 601 | D14: 158-127-181
A15: Next | B15: Steve Bruce | C15: 531
A16: Next | B16: Mauricio Pochettino | C16: 520
A17: Next | B17: Roy Hodgson | C17: 510
A18: Next | B18: Mikel Arteta (active) | C18: 507
A20: Notes
A21: Points = 3 per win + 1 per draw. No tie at 10th.
A22: Redknapp and Allardyce may be 1 to 2 out due to source game-count gaps; positions unaffected.

Sheet Mgr Clubs
A1: Most different Premier League clubs managed
A2: Premier League only, 1992/93 to present (as at 1 Oct 2026; 2026/27 to matchweek 5)
A4: Rank | B4: Manager | C4: Clubs | D4: Which clubs
A5: 1 | B5: Sam Allardyce | C5: 9 | D5: Bolton, Newcastle, Blackburn, West Ham, Sunderland, Crystal Palace, Everton, West Brom, Leeds
A6: =2 -> 2 | B6: Roy Hodgson | C6: 6 | D6: Blackburn, Fulham, Liverpool, West Brom, Crystal Palace, Watford
A7: =2 -> 2 | B7: Mark Hughes | C7: 6 | D7: Blackburn, Man City, Fulham, QPR, Stoke, Southampton
A8: =4 -> 4 | B8: Harry Redknapp | C8: 5 | D8: West Ham, Portsmouth, Southampton, Spurs, QPR
A9: =4 -> 4 | B9: Steve Bruce | C9: 5 | D9: Birmingham, Wigan, Sunderland, Hull, Newcastle
A10: =4 -> 4 | B10: Alan Pardew | C10: 5 | D10: West Ham, Charlton, Newcastle, Crystal Palace, West Brom
A11: =7 -> 7 | B11: Ron Atkinson | C11: 4 | D11: Aston Villa, Coventry, Sheffield Wednesday, Nottingham Forest
A12: =7 -> 7 | B12: Rafael Benítez | C12: 4 | D12: Liverpool, Chelsea, Newcastle, Everton
A13: =7 -> 7 | B13: David Moyes | C13: 4 | D13: Everton, Man Utd, Sunderland, West Ham
A14: =7 -> 7 | B14: Nuno Espírito Santo | C14: 4 | D14: Wolves, Spurs, Nottingham Forest, West Ham
A15: =7 -> 7 | B15: Claudio Ranieri | C15: 4 | D15: Chelsea, Leicester, Fulham, Watford
A16: =7 -> 7 | B16: Marco Silva | C16: 4 | D16: Hull, Watford, Everton, Fulham
A17: =7 -> 7 | B17: Graeme Souness | C17: 4 | D17: Liverpool, Southampton, Blackburn, Newcastle
A18: =7 -> 7 | B18: Neil Warnock | C18: 4 | D18: Sheffield Utd, QPR, Crystal Palace, Cardiff
A20: Notes
A21: 14 valid answers: 8 managers tied on 4 clubs (highlighted).
A22: Edge case: Chris Hughton has 3 (Newcastle, Norwich, Brighton); 4 only if 1990s Spurs caretaker spells count, which are usually credited to David Pleat. Not included.
A23: Caretaker spells count where they are PL games.

Sheet Mgr Titles
A1: Most Premier League titles as manager
A2: Premier League seasons 1992/93 to 2025/26
A4: Rank | B4: Manager | C4: Titles | D4: Seasons / club
A5: 1 | B5: Alex Ferguson | C5: 13 | D5: 92/93, 93/94, 95/96, 96/97, 98/99, 99/00, 00/01, 02/03, 06/07, 07/08, 08/09, 10/11, 12/13 (Man Utd)
A6: 2 | B6: Pep Guardiola | C6: 6 | D6: 17/18, 18/19, 20/21, 21/22, 22/23, 23/24 (Man City)
A7: =3 -> 3 | B7: José Mourinho | C7: 3 | D7: 04/05, 05/06, 14/15 (Chelsea)
A8: =3 -> 3 | B8: Arsène Wenger | C8: 3 | D8: 97/98, 01/02, 03/04 (Arsenal)
A9: =5 -> 5 | B9: Kenny Dalglish | C9: 1 | D9: 94/95 (Blackburn)
A10: =5 -> 5 | B10: Carlo Ancelotti | C10: 1 | D10: 09/10 (Chelsea)
A11: =5 -> 5 | B11: Roberto Mancini | C11: 1 | D11: 11/12 (Man City)
A12: =5 -> 5 | B12: Manuel Pellegrini | C12: 1 | D12: 13/14 (Man City)
A13: =5 -> 5 | B13: Claudio Ranieri | C13: 1 | D13: 15/16 (Leicester)
A14: =5 -> 5 | B14: Antonio Conte | C14: 1 | D14: 16/17 (Chelsea)
A15: =5 -> 5 | B15: Jürgen Klopp | C15: 1 | D15: 19/20 (Liverpool)
A16: =5 -> 5 | B16: Arne Slot | C16: 1 | D16: 24/25 (Liverpool)
A17: =5 -> 5 | B17: Mikel Arteta | C17: 1 | D17: 25/26 (Arsenal, 85 pts)
A19: Notes
A20: 13 valid answers: every PL title-winning manager. 9 tied on 1 (highlighted).

Sheet Mgr Win %
A1: Best Premier League win percentage (minimum 50 games)
A2: Premier League only, 1992/93 to present (as at 1 Oct 2026; 2026/27 to matchweek 5)
A4: Rank | B4: Manager | C4: Wins | D4: Games | E4: Win % | F4: Clubs
A5: 1 | B5: Pep Guardiola | C5: 269 | D5: 380 | E5: =C5/D5 -> 0.70789474 | F5: Man City
A6: 2 | B6: Alex Ferguson | C6: 528 | D6: 810 | E6: =C6/D6 -> 0.65185185 | F6: Man Utd
A7: 3 | B7: Antonio Conte | C7: 83 | D7: 132 | E7: =C7/D7 -> 0.62878788 | F7: Chelsea, Spurs
A8: 4 | B8: Jürgen Klopp | C8: 209 | D8: 334 | E8: =C8/D8 -> 0.6257485 | F8: Liverpool
A9: 5 | B9: Roberto Mancini | C9: 83 | D9: 134 | E9: =C9/D9 -> 0.61940299 | F9: Man City
A10: 6 | B10: Mikel Arteta (active) | C10: 153 | D10: 253 | E10: =C10/D10 -> 0.60474308 | F10: Arsenal
A11: 7 | B11: José Mourinho | C11: 217 | D11: 363 | E11: =C11/D11 -> 0.59779614 | F11: Chelsea, Man Utd, Spurs
A12: 8 | B12: Arsène Wenger | C12: 476 | D12: 828 | E12: =C12/D12 -> 0.57487923 | F12: Arsenal
A13: 9 | B13: Thomas Tuchel | C13: 35 | D13: 63 | E13: =C13/D13 -> 0.55555556 | F13: Chelsea
A14: 10 | B14: Arne Slot | C14: 42 | D14: 76 | E14: =C14/D14 -> 0.55263158 | F14: Liverpool
A15: Next | B15: Carlo Ancelotti | C15: 73 | D15: 134 | E15: =C15/D15 -> 0.54477612 | F15: Chelsea, Everton
A16: Next | B16: Enzo Maresca (active) | C16: 33 | D16: 62 | E16: =C16/D16 -> 0.53225806 | F16: Chelsea, Man City; 5/5 this season, could enter top 10
A17: Next | B17: Manuel Pellegrini | C17: 90 | D17: 171 | E17: =C17/D17 -> 0.52631579 | F17: Man City, West Ham
A19: Notes
A20: Win % = wins / games (formula). No tie at 10th.
A21: Excluded under 50 games: Carrick, Scolari, Sarri, Hiddink, all short caretaker spells.
A22: Mancini sometimes shown as 133 games (62.4%); still 5th.

Sheet Season Goals
A1: Highest single-season Premier League goal totals by a player
A2: Premier League seasons 1992/93 to 2025/26
A4: Rank | B4: Player | C4: Goals | D4: Season | E4: Club / notes
A5: 1 | B5: Erling Haaland | C5: 36 | D5: 22/23 | E5: Man City
A6: =2 -> 2 | B6: Andy Cole | C6: 34 | D6: 93/94 | E6: Newcastle (42-game season)
A7: =2 -> 2 | B7: Alan Shearer | C7: 34 | D7: 94/95 | E7: Blackburn (42-game season)
A8: 4 | B8: Mohamed Salah | C8: 32 | D8: 17/18 | E8: Liverpool
A9: =5 -> 5 | B9: Alan Shearer | C9: 31 | D9: 93/94 | E9: Blackburn (42-game season)
A10: =5 -> 5 | B10: Alan Shearer | C10: 31 | D10: 95/96 | E10: Blackburn
A11: =5 -> 5 | B11: Cristiano Ronaldo | C11: 31 | D11: 07/08 | E11: Man Utd
A12: =5 -> 5 | B12: Luis Suárez | C12: 31 | D12: 13/14 | E12: Liverpool
A13: =9 -> 9 | B13: Kevin Phillips | C13: 30 | D13: 99/00 | E13: Sunderland
A14: =9 -> 9 | B14: Thierry Henry | C14: 30 | D14: 03/04 | E14: Arsenal
A15: =9 -> 9 | B15: Robin van Persie | C15: 30 | D15: 11/12 | E15: Arsenal
A16: =9 -> 9 | B16: Harry Kane | C16: 30 | D16: 17/18 | E16: Spurs
A17: =9 -> 9 | B17: Harry Kane | C17: 30 | D17: 22/23 | E17: Spurs
A18: Next | B18: Mohamed Salah | C18: 29 | D18: 24/25
A19: Next | B19: Harry Kane | C19: 29 | D19: 16/17
A20: Next | B20: Didier Drogba | C20: 29 | D20: 09/10
A22: Notes
A23: 13 valid entries: 5 seasons tied on 30 (highlighted).
A24: Shearer fills 3 slots and Kane 2 (within the max-3 rule). If answers are player names, decide whether a repeat name scores once or per slot.
A25: Shearer's 31 in 93/94 is missing from Golden Boot winners lists because Cole won that year.
A26: Haaland 25/26 = 27 (Golden Boot), not enough for this list.

Sheet 20+ Seasons
A1: Every 20+ goal Premier League season by a player
A2: Premier League seasons 1992/93 to 2025/26
A4: Season | B4: Player | C4: Club | D4: Goals
A5: 92/93 | B5: Teddy Sheringham | C5: Nottm Forest / Spurs | D5: 22
A6: 92/93 | B6: Les Ferdinand | C6: QPR | D6: 20
A7: 93/94 | B7: Andy Cole | C7: Newcastle | D7: 34
A8: 93/94 | B8: Alan Shearer | C8: Blackburn | D8: 31
A9: 93/94 | B9: Matt Le Tissier | C9: Southampton | D9: 25
A10: 93/94 | B10: Chris Sutton | C10: Norwich | D10: 25
A11: 93/94 | B11: Ian Wright | C11: Arsenal | D11: 23
A12: 93/94 | B12: Peter Beardsley | C12: Newcastle | D12: 21
A13: 94/95 | B13: Alan Shearer | C13: Blackburn | D13: 34
A14: 94/95 | B14: Robbie Fowler | C14: Liverpool | D14: 25
A15: 94/95 | B15: Les Ferdinand | C15: QPR | D15: 24
A16: 94/95 | B16: Stan Collymore | C16: Nottm Forest | D16: 22
... A103: 25/26 | B103: Igor Thiago | C103: Brentford | D103: 22
A105: Notes
A106: 99 instances. No player reached 20 in 97/98, 98/99 or 08/09.
A107: Split-club totals combined: Sheringham 92/93, Cole 94/95, Saha 03/04.
A108: Cross-checked season by season against Wikipedia season pages and Football365's club breakdown.

Sheet 20+ Players
A1: Every player to score 20+ PL goals in a season
A2: Premier League seasons 1992/93 to 2025/26
A4: # | B4: Player | C4: 20+ seasons | D4: Best | E4: Seasons (goals)
A5: 1 | B5: Alan Shearer | C5: =COUNTIF('20+ Seasons'!$B$5:$B$103,B5) -> 7 | D5: =SUMPRODUCT(MAX(('20+ Seasons'!$B$5:$B$103=B5)*'20+ Seasons'!$D$5:$D$103)) -> 34 | E5: 93/94 (31), 94/95 (34), 95/96 (31), 96/97 (25), 99/00 (23), 01/02 (23), 03/04 (22)
A6: 2 | B6: Sergio Agüero | C6: =COUNTIF('20+ Seasons'!$B$5:$B$103,B6) -> 6 | D6: =SUMPRODUCT(MAX(('20+ Seasons'!$B$5:$B$103=B6)*'20+ Seasons'!$D$5:$D$103)) -> 26 | E6: 11/12 (23), 14/15 (26), 15/16 (24), 16/17 (20), 17/18 (21), 18/19 (21)
A7: 3 | B7: Harry Kane | C7: =COUNTIF('20+ Seasons'!$B$5:$B$103,B7) -> 6 | D7: =SUMPRODUCT(MAX(('20+ Seasons'!$B$5:$B$103=B7)*'20+ Seasons'!$D$5:$D$103)) -> 30 | E7: 14/15 (21), 15/16 (25), 16/17 (29), 17/18 (30), 20/21 (23), 22/23 (30)
A8: 4 | B8: Thierry Henry | C8: =COUNTIF('20+ Seasons'!$B$5:$B$103,B8) -> 5 | D8: =SUMPRODUCT(MAX(('20+ Seasons'!$B$5:$B$103=B8)*'20+ Seasons'!$D$5:$D$103)) -> 30 | E8: 01/02 (24), 02/03 (24), 03/04 (30), 04/05 (25), 05/06 (27)
A9: 5 | B9: Mohamed Salah | C9: =COUNTIF('20+ Seasons'!$B$5:$B$103,B9) -> 5 | D9: =SUMPRODUCT(MAX(('20+ Seasons'!$B$5:$B$103=B9)*'20+ Seasons'!$D$5:$D$103)) -> 32 | E9: 17/18 (32), 18/19 (22), 20/21 (22), 21/22 (23), 24/25 (29)
A10: 6 | B10: Ruud van Nistelrooy | C10: =COUNTIF('20+ Seasons'!$B$5:$B$103,B10) -> 4 | D10: =SUMPRODUCT(MAX(('20+ Seasons'!$B$5:$B$103=B10)*'20+ Seasons'!$D$5:$D$103)) -> 25 | E10: 01/02 (23), 02/03 (25), 03/04 (20), 05/06 (21)
A11: 7 | B11: Erling Haaland | C11: =COUNTIF('20+ Seasons'!$B$5:$B$103,B11) -> 4 | D11: =SUMPRODUCT(MAX(('20+ Seasons'!$B$5:$B$103=B11)*'20+ Seasons'!$D$5:$D$103)) -> 36 | E11: 22/23 (36), 23/24 (27), 24/25 (22), 25/26 (27)
A12: 8 | B12: Les Ferdinand | C12: =COUNTIF('20+ Seasons'!$B$5:$B$103,B12) -> 3 | D12: =SUMPRODUCT(MAX(('20+ Seasons'!$B$5:$B$103=B12)*'20+ Seasons'!$D$5:$D$103)) -> 25 | E12: 92/93 (20), 94/95 (24), 95/96 (25)
A13: 9 | B13: Jamie Vardy | C13: =COUNTIF('20+ Seasons'!$B$5:$B$103,B13) -> 3 | D13: =SUMPRODUCT(MAX(('20+ Seasons'!$B$5:$B$103=B13)*'20+ Seasons'!$D$5:$D$103)) -> 24 | E13: 15/16 (24), 17/18 (20), 19/20 (23)
A14: 10 | B14: Andy Cole | C14: =COUNTIF('20+ Seasons'!$B$5:$B$103,B14) -> 2 | D14: =SUMPRODUCT(MAX(('20+ Seasons'!$B$5:$B$103=B14)*'20+ Seasons'!$D$5:$D$103)) -> 34 | E14: 93/94 (34), 94/95 (21)
A15: 11 | B15: Ian Wright | C15: =COUNTIF('20+ Seasons'!$B$5:$B$103,B15) -> 2 | D15: =SUMPRODUCT(MAX(('20+ Seasons'!$B$5:$B$103=B15)*'20+ Seasons'!$D$5:$D$103)) -> 23 | E15: 93/94 (23), 96/97 (23)
A16: 12 | B16: Robbie Fowler | C16: =COUNTIF('20+ Seasons'!$B$5:$B$103,B16) -> 2 | D16: =SUMPRODUCT(MAX(('20+ Seasons'!$B$5:$B$103=B16)*'20+ Seasons'!$D$5:$D$103)) -> 28 | E16: 94/95 (25), 95/96 (28)
... A57: 53 | B57: Igor Thiago | C57: =COUNTIF('20+ Seasons'!$B$5:$B$103,B57) -> 1 | D57: =SUMPRODUCT(MAX(('20+ Seasons'!$B$5:$B$103=B57)*'20+ Seasons'!$D$5:$D$103)) -> 22 | E57: 25/26 (22)
A59: Notes
A60: 53 valid answers. 20+ seasons count uses COUNTIF on the '20+ Seasons' tab; Best uses MAX of that player's goals.
A61: For a top-10 'most 20+ seasons' board: Shearer 7, Kane 6, Agüero 6, Henry 5, Salah 5, Van Nistelrooy 4, Haaland 4, Ferdinand 3, Vardy 3, then 12 players tied on 2.

Sheet Seasons Played
A1: Most Premier League seasons played by a player
A2: Premier League only, 1992/93 to present (as at 1 Oct 2026; 2026/27 to matchweek 5)
A4: Rank | B4: Player | C4: Seasons | D4: PL apps | E4: Span / clubs
A5: 1 | B5: James Milner (retired June 2026) | C5: 24 | D5: 658 | E5: 2002/03-2025/26: Leeds, Newcastle, Aston Villa, Man City, Liverpool, Brighton
A6: 2 | B6: Ryan Giggs | C6: 22 | D6: 632 | E6: 1992/93-2013/14: Man Utd
A7: 3 | B7: Gareth Barry | C7: 21 | D7: 653 | E7: 1997/98-2017/18: Aston Villa, Man City, Everton, West Brom
A8: =4 -> 4 | B8: Frank Lampard | C8: 20 | D8: 609 | E8: 1995/96-2014/15: West Ham, Chelsea, Man City
A9: =4 -> 4 | B9: Rio Ferdinand | C9: 20 | D9: 504 | E9: 1995/96-2014/15: West Ham, Leeds, Man Utd, QPR
A10: =6 -> 6 | B10: Danny Welbeck (active) | C10: 19 | D10: 403 | E10: 2008/09-2026/27: Man Utd, Sunderland, Arsenal, Watford, Brighton, Chelsea. VERIFY 2026/27 apps
A11: =6 -> 6 | B11: Jermain Defoe | C11: 19 | D11: 496 | E11: 2000/01-2018/19: West Ham, Spurs, Portsmouth, Sunderland, Bournemouth
A12: =6 -> 6 | B12: John Terry | C12: 19 | D12: 492 | E12: 1998/99-2016/17: Chelsea
A13: =6 -> 6 | B13: Paul Scholes | C13: 19 | D13: 499 | E13: 1994/95-2012/13: Man Utd
A14: =6 -> 6 | B14: Phil Neville | C14: 19 | D14: 505 | E14: 1994/95-2012/13: Man Utd, Everton
A15: =6 -> 6 | B15: Sol Campbell | C15: 19 | D15: 503 | E15: 1992/93-2010/11: Spurs, Arsenal, Portsmouth, Newcastle
A16: =6 -> 6 | B16: Shay Given | C16: 19 | D16: 451 | E16: 1996/97-2016/17 (gaps 10/11, 13/14): Blackburn, Newcastle, Man City, Villa, Stoke
A17: Next | B17: Jonny Evans | C17: 18 | D17: 386
A18: Next | B18: Ashley Young | C18: 18 | D18: 485
A19: Next | B19: Peter Crouch | C19: 18 | D19: 468
A20: Next | B20: Michael Carrick | C20: 18 | D20: 481
A21: Next | B21: Mark Schwarzer | C21: 18 | D21: 514
A22: Next | B22: David James | C22: 18 | D22: 572
A24: Notes
A25: 12 valid answers: 7 tied on 19 (highlighted).
A26: A season counts if the player made at least one PL appearance.
A27: Welbeck's 19th season relies on 3 Chelsea apps in 2026/27 from a single source. Check before use; without it he drops to 18 and the board has 11 answers.

Sheet Signings
A1: Most expensive transfers into Premier League clubs (headline fee)
A2: All-time, to 1 Sept 2026 window close
A4: Rank | B4: Player | C4: Fee (£m) | D4: Move | E4: Year / notes
A5: =1 -> 1 | B5: Alexander Isak | C5: 125 | D5: Newcastle to Liverpool | E5: 2025
A6: =1 -> 1 | B6: Enzo Fernández | C6: 125 | D6: Chelsea to Man City | E6: 2026
A7: 3 | B7: Bradley Barcola | C7: 123 | D7: PSG to Liverpool | E7: 2026
A8: 4 | B8: Morgan Rogers | C8: 117 | D8: Aston Villa to Chelsea | E8: 2026
A9: =5 -> 5 | B9: Elliot Anderson | C9: 116 | D9: Nottm Forest to Man City | E9: 2026
A10: =5 -> 5 | B10: Florian Wirtz | C10: 116 | D10: Leverkusen to Liverpool | E10: 2025
A11: 7 | B11: Moisés Caicedo | C11: 115 | D11: Brighton to Chelsea | E11: 2023
A12: 8 | B12: Enzo Fernández | C12: 106.8 | D12: Benfica to Chelsea | E12: 2023
A13: 9 | B13: Declan Rice | C13: 105 | D13: West Ham to Arsenal | E13: 2023
A14: =10 -> 10 | B14: Jack Grealish | C14: 100 | D14: Aston Villa to Man City | E14: 2021
A15: =10 -> 10 | B15: Sandro Tonali | C15: 100 | D15: Newcastle to Spurs | E15: 2026
A16: Next | B16: Romelu Lukaku | C16: 97.5 | D16: Inter to Chelsea | E16: 2021
A17: Next | B17: Paul Pogba | C17: 89 | D17: Juventus to Man Utd | E17: 2016
A19: Notes
A20: 11 valid answers (Grealish and Tonali tied, highlighted).
A21: Includes PL-to-PL moves. Enzo Fernández fills 2 slots.
A22: On guaranteed fees only the order changes and Tonali drops out.
A23: Isak sometimes quoted £130m (incl. solidarity payments).

Sheet Sales Any
A1: Biggest sales by Premier League clubs, any buyer (guaranteed fee)
A2: All-time, to 1 Sept 2026
A4: Rank | B4: Player | C4: Fee (£m) | D4: Move | E4: Headline / max
A5: =1 -> 1 | B5: Alexander Isak | C5: 125 | D5: Newcastle to Liverpool
A6: =1 -> 1 | B6: Enzo Fernández | C6: 125 | D6: Chelsea to Man City
A7: 3 | B7: Morgan Rogers | C7: 117 | D7: Aston Villa to Chelsea
A8: 4 | B8: Elliot Anderson | C8: 116 | D8: Nottm Forest to Man City
A9: 5 | B9: Philippe Coutinho | C9: 105 | D9: Liverpool to Barcelona | E9: up to £142m
A10: =6 -> 6 | B10: Jack Grealish | C10: 100 | D10: Aston Villa to Man City
A11: =6 -> 6 | B11: Declan Rice | C11: 100 | D11: West Ham to Arsenal | E11: £105m
A12: =6 -> 6 | B12: Moisés Caicedo | C12: 100 | D12: Brighton to Chelsea | E12: £115m
A13: 9 | B13: Sandro Tonali | C13: 92.5 | D13: Newcastle to Spurs | E13: £100m
A14: 10 | B14: Eden Hazard | C14: 88.5 | D14: Chelsea to Real Madrid | E14: up to £130m
A15: Next | B15: Harry Kane | C15: 86.4 | D15: Spurs to Bayern
A16: Next | B16: Gareth Bale | C16: 85.3 | D16: Spurs to Real Madrid
A18: Notes
A19: Overlaps heavily with Signings tab. 'Sales Abroad' is the better quiz board.

Sheet Sales Abroad
A1: Biggest sales by Premier League clubs to clubs outside the PL (guaranteed fee)
A2: All-time, to 1 Sept 2026
A4: Rank | B4: Player | C4: Fee (£m) | D4: Move | E4: Headline / max
A5: 1 | B5: Philippe Coutinho | C5: 105 | D5: Liverpool to Barcelona (2018) | E5: up to £142m
A6: 2 | B6: Eden Hazard | C6: 88.5 | D6: Chelsea to Real Madrid (2019) | E6: up to £130m
A7: 3 | B7: Harry Kane | C7: 86.4 | D7: Spurs to Bayern (2023) | E7: £100m+ reported
A8: 4 | B8: Gareth Bale | C8: 85.3 | D8: Spurs to Real Madrid (2013)
A9: 5 | B9: Cristiano Ronaldo | C9: 80 | D9: Man Utd to Real Madrid (2009)
A10: 6 | B10: Romelu Lukaku | C10: 74 | D10: Man Utd to Inter (2019)
A11: 7 | B11: Anthony Gordon | C11: 69.3 | D11: Newcastle to Barcelona (2026)
A12: 8 | B12: Luis Díaz | C12: 65.5 | D12: Liverpool to Bayern (2025)
A13: 9 | B13: Luis Suárez | C13: 65 | D13: Liverpool to Barcelona (2014) | E13: £75m in UK reports at the time
A14: =10 -> 10 | B14: Jhon Durán | C14: 64.5 | D14: Aston Villa to Al-Nassr (2025)
A15: =10 -> 10 | B15: Julián Álvarez | C15: 64.4 | D15: Man City to Atlético (2024) | E15: £81.5m with add-ons
A16: Next | B16: Gabriel Martinelli | C16: 60 | D16: Arsenal to Al Hilal (2026)
A18: Notes
A19: 11 valid answers: Durán and Álvarez are £0.1m apart, treated as tied (highlighted). On headline fees Álvarez would rank higher.

Sheet Club Records
A1: Club record signing and sale
A2: All-time, to 1 Sept 2026 (headline fees)
A4: Club | B4: Record signing | C4: Fee (£m) | D4: Record sale | E4: Fee (£m) | F4: Notes
A5: Man Utd | B5: Paul Pogba (Juventus, 2016) | C5: 89 | D5: Cristiano Ronaldo (Real Madrid, 2009) | E5: 80
A6: Liverpool | B6: Alexander Isak (Newcastle, 2025) | C6: 125 | D6: Philippe Coutinho (Barcelona, 2018) | E6: 142 | F6: Coutinho £105m guaranteed
A7: Arsenal | B7: Declan Rice (West Ham, 2023) | C7: 105 | D7: Gabriel Martinelli (Al Hilal, Sept 2026) | E7: 60 | F7: Previous sale record: Oxlade-Chamberlain c.£35m
A8: Chelsea | B8: Morgan Rogers (Aston Villa, 2026) | C8: 117 | D8: Enzo Fernández (Man City, 2026) | E8: 125
A9: Man City | B9: Enzo Fernández (Chelsea, 2026) | C9: 125 | D9: Savinho (Spurs, 2026) | E9: 85 | F9: Savinho £75m + £10m
A10: Spurs | B10: Sandro Tonali (Newcastle, 2026) | C10: 100 | D10: Harry Kane (Bayern, 2023) | E10: 86.4
A11: Newcastle | B11: Nick Woltemade (Stuttgart, 2025) | C11: 69 | D11: Alexander Isak (Liverpool, 2025) | E11: 125
A12: Aston Villa | B12: Nicolas Jackson (Chelsea, 2026) | C12: 65 | D12: Morgan Rogers (Chelsea, 2026) | E12: 117 | F12: On guaranteed fee, Manzambi £59.5m is Villa's record signing
A13: West Ham | B13: Lucas Paquetá (Lyon, 2022) | C13: 51 | D13: Declan Rice (Arsenal, 2023) | E13: 105 | F13: West Ham relegated May 2026
A14: Everton | B14: Gylfi Sigurdsson (Swansea, 2017) | C14: 45 | D14: Romelu Lukaku (Man Utd, 2017) | E14: 75
A16: Notes
A17: Not a top-10 list. Could become a 10-answer board, e.g. 'name each club's record signing' with the club as the clue.

Sheet GK Signings
A1: Most expensive goalkeeper signings by PL clubs
A2: All-time PL club signings, to 1 Sept 2026 (headline fee; Transfermarkt position groups, wingers = forwards)
A4: Rank | B4: Player | C4: Fee (£m) | D4: Move | E4: Year / notes
A5: 1 | B5: Kepa Arrizabalaga | C5: 71.6 | D5: Athletic to Chelsea | E5: 2018
A6: 2 | B6: Alisson | C6: 66.8 | D6: Roma to Liverpool | E6: 2018
A7: 3 | B7: André Onana | C7: 47.2 | D7: Inter to Man Utd | E7: 2023
A8: 4 | B8: James Trafford | C8: 45 | D8: Man City to Leeds | E8: 2026
A9: 5 | B9: Ederson | C9: 34.9 | D9: Benfica to Man City | E9: 2017
A10: 6 | B10: James Trafford | C10: 31 | D10: Burnley to Man City | E10: 2025
A11: =7 -> 7 | B11: Jordan Pickford | C11: 30 | D11: Sunderland to Everton | E11: 2017
A12: =7 -> 7 | B12: Aaron Ramsdale | C12: 30 | D12: Sheffield Utd to Arsenal | E12: 2021
A13: 9 | B13: Giorgi Mamardashvili | C13: 29 | D13: Valencia to Liverpool | E13: 2024/25
A14: 10 | B14: David Raya | C14: 27 | D14: Brentford to Arsenal | E14: 2024
A15: Next | B15: Gianluigi Donnarumma | C15: 26 | D15: PSG to Man City | E15: 2025
A17: Notes
A18: Trafford fills 2 slots.
A19: Raya becomes £30m (joint 7th) if his £3m loan fee is added.

Sheet DEF Signings
A1: Most expensive defender signings by PL clubs
A2: All-time PL club signings, to 1 Sept 2026 (headline fee; Transfermarkt position groups, wingers = forwards)
A4: Rank | B4: Player | C4: Fee (£m) | D4: Move | E4: Year / notes
A5: 1 | B5: Harry Maguire | C5: 80 | D5: Leicester to Man Utd | E5: 2019
A6: 2 | B6: Joško Gvardiol | C6: 77.6 | D6: Leipzig to Man City | E6: 2023
A7: =3 -> 3 | B7: Virgil van Dijk | C7: 75 | D7: Southampton to Liverpool | E7: 2018
A8: =3 -> 3 | B8: Wesley Fofana | C8: 75 | D8: Leicester to Chelsea | E8: 2022
A9: 5 | B9: Rúben Dias | C9: 65 | D9: Benfica to Man City | E9: 2020
A10: 6 | B10: Marc Cucurella | C10: 62 | D10: Brighton to Chelsea | E10: 2022
A11: =7 -> 7 | B11: João Cancelo | C11: 60 | D11: Juventus to Man City | E11: 2019
A12: =7 -> 7 | B12: Jérémy Jacquet | C12: 60 | D12: Rennes to Liverpool | E12: 2026
A13: 9 | B13: Leny Yoro | C13: 59.9 | D13: Lille to Man Utd | E13: 2024
A14: 10 | B14: Aymeric Laporte | C14: 57 | D14: Athletic to Man City | E14: 2018
A15: Next | B15: Lisandro Martínez | C15: 56.7 | D15: Ajax to Man Utd | E15: 2022
A16: Next | B16: Ezri Konsa | C16: 55 | D16: Aston Villa to Arsenal | E16: 2026
A18: Notes
A19: No tie at 10th. Guéhi moved to Man City Jan 2026 for only £20m.

Sheet MID Signings
A1: Most expensive midfielder signings by PL clubs
A2: All-time PL club signings, to 1 Sept 2026 (headline fee; Transfermarkt position groups, wingers = forwards)
A4: Rank | B4: Player | C4: Fee (£m) | D4: Move | E4: Year / notes
A5: 1 | B5: Enzo Fernández | C5: 125 | D5: Chelsea to Man City | E5: 2026
A6: 2 | B6: Morgan Rogers | C6: 117 | D6: Aston Villa to Chelsea | E6: 2026 (debatable: some class as forward)
A7: =3 -> 3 | B7: Elliot Anderson | C7: 116 | D7: Nottm Forest to Man City | E7: 2026
A8: =3 -> 3 | B8: Florian Wirtz | C8: 116 | D8: Leverkusen to Liverpool | E8: 2025
A9: 5 | B9: Moisés Caicedo | C9: 115 | D9: Brighton to Chelsea | E9: 2023
A10: 6 | B10: Enzo Fernández | C10: 106.8 | D10: Benfica to Chelsea | E10: 2023
A11: 7 | B11: Declan Rice | C11: 105 | D11: West Ham to Arsenal | E11: 2023
A12: 8 | B12: Sandro Tonali | C12: 100 | D12: Newcastle to Spurs | E12: 2026
A13: 9 | B13: Paul Pogba | C13: 89 | D13: Juventus to Man Utd | E13: 2016
A14: 10 | B14: Ayyoub Bouaddi | C14: 86 | D14: Lille to Man City | E14: 2026
A15: Next | B15: Mateus Fernandes | C15: 85 | D15: West Ham to Spurs | E15: 2026
A17: Notes
A18: Enzo Fernández fills 2 slots.
A19: If Rogers is treated as a forward, Mateus Fernandes enters at 10th here.

Sheet FWD Signings
A1: Most expensive forward signings by PL clubs (incl. wingers)
A2: All-time PL club signings, to 1 Sept 2026 (headline fee; Transfermarkt position groups, wingers = forwards)
A4: Rank | B4: Player | C4: Fee (£m) | D4: Move | E4: Year / notes
A5: 1 | B5: Alexander Isak | C5: 125 | D5: Newcastle to Liverpool | E5: 2025
A6: 2 | B6: Bradley Barcola | C6: 123 | D6: PSG to Liverpool | E6: 2026
A7: 3 | B7: Jack Grealish | C7: 100 | D7: Aston Villa to Man City | E7: 2021
A8: 4 | B8: Romelu Lukaku | C8: 97.5 | D8: Inter to Chelsea | E8: 2021
A9: 5 | B9: Romelu Lukaku | C9: 90 | D9: Everton to Man Utd | E9: 2017
A10: 6 | B10: Mykhailo Mudryk | C10: 88.5 | D10: Shakhtar to Chelsea | E10: 2023
A11: 7 | B11: Antony | C11: 85.5 | D11: Ajax to Man Utd | E11: 2022
A12: =8 -> 8 | B12: Savinho | C12: 85 | D12: Man City to Spurs | E12: 2026
A13: =8 -> 8 | B13: Darwin Núñez | C13: 85 | D13: Benfica to Liverpool | E13: 2022
A14: 10 | B14: Hugo Ekitike | C14: 79 | D14: Frankfurt to Liverpool | E14: 2025
A15: Next | B15: Benjamin Šeško | C15: 73.7 | D15: Leipzig to Man Utd | E15: 2025
A17: Notes
A18: Lukaku fills 2 slots.
A19: If Rogers is classed as a forward he goes in at 3rd (£117m) and Ekitike drops out.

Sheet Hat-tricks
A1: Most Premier League hat-tricks
A2: Premier League only, 1992/93 to present (as at 1 Oct 2026; 2026/27 to matchweek 5)
A4: Rank | B4: Player | C4: Hat-tricks
A5: 1 | B5: Sergio Agüero | C5: 12
A6: 2 | B6: Alan Shearer | C6: 11
A7: 3 | B7: Robbie Fowler | C7: 9
A8: =4 -> 4 | B8: Erling Haaland | C8: 8
A9: =4 -> 4 | B9: Thierry Henry | C9: 8
A10: =4 -> 4 | B10: Harry Kane | C10: 8
A11: =4 -> 4 | B11: Michael Owen | C11: 8
A12: 8 | B12: Wayne Rooney | C12: 7
A13: 9 | B13: Luis Suárez | C13: 6
A14: =10 -> 10 | B14: Dimitar Berbatov | C14: 5
A15: =10 -> 10 | B15: Andy Cole | C15: 5
A16: =10 -> 10 | B16: Ruud van Nistelrooy | C16: 5
A17: =10 -> 10 | B17: Robin van Persie | C17: 5
A18: =10 -> 10 | B18: Raheem Sterling | C18: 5
A19: =10 -> 10 | B19: Ian Wright | C19: 5
A21: Notes
A22: 15 valid answers: 6 tied on 5 (highlighted).
A23: Live list: recheck the latest round before use (source updated 20 Sept 2026). Haaland has none since 2024/25.
A24: Many players on 4 (Salah, Son, Palmer and others), one short of the cut-off.

Sheet Fastest 50
A1: Fastest to 50 Premier League goals (games taken)
A2: Premier League seasons 1992/93 to 2025/26
A4: Rank | B4: Player | C4: Games
A5: 1 | B5: Erling Haaland | C5: 48
A6: 2 | B6: Andy Cole | C6: 65
A7: 3 | B7: Alan Shearer | C7: 66
A8: 4 | B8: Ruud van Nistelrooy | C8: 68
A9: =5 -> 5 | B9: Fernando Torres | C9: 72
A10: =5 -> 5 | B10: Mohamed Salah | C10: 72
A11: 7 | B11: Alexander Isak | C11: 76
A12: 8 | B12: Pierre-Emerick Aubameyang | C12: 79
A13: 9 | B13: Sergio Agüero | C13: 81
A14: =10 -> 10 | B14: Thierry Henry | C14: 83
A15: =10 -> 10 | B15: Kevin Phillips | C15: 83
A16: Next | B16: Diego Costa | C16: 85
A18: Notes
A19: 11 valid answers (Henry and Phillips tied, highlighted).

Sheet Fastest 100
A1: Fastest to 100 Premier League goals (games taken)
A2: Premier League seasons 1992/93 to 2025/26
A4: Rank | B4: Player | C4: Games | D4: 100th goal
A5: 1 | B5: Erling Haaland | C5: 111 | D5: vs Fulham, 2 Dec 2025
A6: 2 | B6: Alan Shearer | C6: 124 | D6: vs Spurs, 30 Dec 1995
A7: 3 | B7: Harry Kane | C7: 141 | D7: vs Liverpool, 4 Feb 2018
A8: 4 | B8: Sergio Agüero | C8: 147 | D8: vs Newcastle, 19 Apr 2016
A9: 5 | B9: Thierry Henry | C9: 160 | D9: vs Southampton, 10 Feb 2004
A10: 6 | B10: Mohamed Salah | C10: 162 | D10: vs Leeds, 12 Sep 2021
A11: 7 | B11: Ian Wright | C11: 173 | D11: vs Bolton, 13 Sep 1997
A12: 8 | B12: Robbie Fowler | C12: 175 | D12: vs Southampton, 16 Jan 1999
A13: 9 | B13: Les Ferdinand | C13: 178 | D13: vs Nottm Forest, 11 May 1997
A14: =10 -> 10 | B14: Michael Owen | C14: 185 | D14: vs West Brom, 26 Apr 2003
A15: =10 -> 10 | B15: Andy Cole | C15: 185
A16: Next | B16: Robin van Persie | C16: 197
A18: Notes
A19: 11 valid answers (Owen and Cole tied, highlighted).
A20: Andy Cole's 185 is the least well sourced figure; verify if possible.
A21: Shearer sometimes quoted as 121; Premier League official figure 124 used.

Sheet Sources
A1: Main sources
A3: https://en.wikipedia.org/wiki/List_of_Premier_League_managers
A4: https://www.statmuse.com/fc
A5: https://www.mancity.com/news/mens/pep-guardiola-manchester-city-stats-records-63915079
A6: https://theanalyst.com/2024/05/most-premier-league-games-by-managers
A7: https://en.wikipedia.org/wiki/Premier_League_Golden_Boot
A8: https://en.wikipedia.org/wiki/List_of_Premier_League_hat-tricks
A9: https://www.myfootballfacts.com/premier-league/all-time-premier-league/top-scorers/all-time-premier-league-hat-tricks/
A10: https://theanalyst.com/articles/the-fastest-players-to-50-premier-league-goals
A11: https://theanalyst.com/articles/fastest-players-to-100-premier-league-goals
A12: https://www.premierleague.com/en/news/4455995/erling-haaland-scores-100th-premier-league-goal-in-record-number-of-matches
A13: https://www.football365.com/news/20-goal-premier-league-seasons-the-statistics
... A20: https://www.football365.com/news/most-expensive-defenders-ever-maguire-man-utd-manchester-city
